ultima_scraper/__init__.py
ultima_scraper/api.py
ultima_scraper/docs/assets/img/1.png
ultima_scraper/docs/assets/img/2.png
ultima_scraper/docs/assets/img/3.png
ultima_scraper/docs/assets/img/4.png
ultima_scraper/docs/assets/img/5.png
ultima_scraper/docs/assets/img/64255399-96a86700-cf21-11e9-8c62-87a483f33701.png
ultima_scraper/docs/assets/img/icon.ico
ultima_scraper/managers/dashboard_controller_api.py
ultima_scraper/managers/ui_manager.py
ultima_scraper/py.typed
ultima_scraper/ultima_scraper.py
ultima_scraper-9.0.15.dist-info/LICENSE
ultima_scraper-9.0.15.dist-info/METADATA
ultima_scraper-9.0.15.dist-info/WHEEL
ultima_scraper-9.0.15.dist-info/RECORD
