Metadata-Version: 2.1
Name: ultima-scraper
Version: 9.0.15
Summary: 
License: GPL-3.0
Author: UltimaHoarder
Author-email: 1285176+UltimaHoarder@users.noreply.github.com
Requires-Python: >=3.10,<3.12
Classifier: License :: OSI Approved :: GNU General Public License v3 (GPLv3)
Classifier: Programming Language :: Python :: 3
Classifier: Programming Language :: Python :: 3.10
Classifier: Programming Language :: Python :: 3.11
Requires-Dist: requests (>=2.26.0,<3.0.0)
Requires-Dist: ultima-scraper-api (>=2.2.20,<3.0.0)
Requires-Dist: ultima-scraper-collection (==2.2.0)
Requires-Dist: ultima-scraper-db (==0.3.1)
Requires-Dist: ultima-scraper-renamer (>=1.0.0,<2.0.0)
